kahi_minciencias_opendata_works/Kahi_minciencias_opendata_works.py
kahi_minciencias_opendata_works/__init__.py
kahi_minciencias_opendata_works/_version.py
kahi_minciencias_opendata_works/parser.py
kahi_minciencias_opendata_works/process_one.py
Kahi_minciencias_opendata_works-0.1.1.dist-info/LICENSE
Kahi_minciencias_opendata_works-0.1.1.dist-info/METADATA
Kahi_minciencias_opendata_works-0.1.1.dist-info/WHEEL
Kahi_minciencias_opendata_works-0.1.1.dist-info/top_level.txt
Kahi_minciencias_opendata_works-0.1.1.dist-info/RECORD
